py2api/__init__.py
py2api/constants.py
py2api/defaults.py
py2api/errors.py
py2api/obj_wrap.py
py2api/output_trans.py
py2api/scrap_obj_wrap.py
py2api/util.py
py2api/examples/__init__.py
py2api/examples/pong.py
py2api/examples/streaming_sine.py
py2api/examples/wrapping_a_class.py
py2api/examples/wrapping_a_module.py
py2api/py2rest/__init__.py
py2api/py2rest/app_maker.py
py2api/py2rest/constants.py
py2api/py2rest/input_trans.py
py2api/py2rest/obj_wrap.py
py2api/py2rest/rest2py.py
py2api-0.0.3.dist-info/LICENSE
py2api-0.0.3.dist-info/METADATA
py2api-0.0.3.dist-info/WHEEL
py2api-0.0.3.dist-info/top_level.txt
py2api-0.0.3.dist-info/RECORD
