Metadata-Version: 2.1
Name: py2api
Version: 0.0.3
Summary: Declarative API entry point
Home-page: https://github.com/thorwhalen/py2api
Author: Otosense
License: mit
Platform: any
License-File: LICENSE
Requires-Dist: flask-cors
Requires-Dist: numpy
Requires-Dist: urlparse
Requires-Dist: flask
Requires-Dist: werkzeug
Requires-Dist: platform
Requires-Dist: requests
